sphinx_click/__init__.py
sphinx_click/ext.py
sphinx_click-6.1.0.dist-info/licenses/LICENSE
sphinx_click-6.1.0.dist-info/METADATA
sphinx_click-6.1.0.dist-info/WHEEL
sphinx_click-6.1.0.dist-info/top_level.txt
sphinx_click-6.1.0.dist-info/RECORD
