Metadata-Version: 2.4
Name: sphinx-click
Version: 6.1.0
Summary: Sphinx extension that automatically documents click applications
Author-email: Stephen Finucane <stephen@that.guru>
License: MIT License
Project-URL: Bug Tracker, https://github.com/click-contrib/sphinx-click/issues
Project-URL: Documentation, https://sphinx-click.readthedocs.io/en/latest
Project-URL: Source Code, https://github.com/click-contrib/sphinx-click
Keywords: sphinx,click
Classifier: Development Status :: 5 - Production/Stable
Classifier: Environment :: Console
Classifier: Framework :: Sphinx :: Extension
Classifier: Intended Audience :: Developers
Classifier: Intended Audience :: Information Technology
Classifier: License :: OSI Approved :: MIT License
Classifier: Operating System :: OS Independent
Classifier: Programming Language :: Python
Classifier: Programming Language :: Python :: 3
Classifier: Programming Language :: Python :: 3 :: Only
Classifier: Topic :: Documentation
Classifier: Topic :: Documentation :: Sphinx
Classifier: Topic :: Utilities
Requires-Python: >=3.10
License-File: LICENSE
Requires-Dist: sphinx>=4.0
Requires-Dist: click>=8.0
Requires-Dist: docutils
Provides-Extra: docs
Requires-Dist: reno; extra == "docs"
Provides-Extra: test
Requires-Dist: pytest; extra == "test"
Requires-Dist: pytest-cov; extra == "test"
Dynamic: license-file
